{
    "os": "Windows-10-10.0.22631-SP0",
    "python": "3.11.0",
    "heartbeatAt": "2024-09-03T21:29:25.794254",
    "startedAt": "2024-09-03T21:29:25.253088",
    "docker": null,
    "cuda": null,
    "args": [],
    "state": "running",
    "program": "c:\\Users\\joaqu\\OneDrive\\Documentos\\FAU\\Project glaciar\\Glaciers_NeurIPS\\DeepLearning\\LSTMTrain\\LSTMTrain.py",
    "codePathLocal": "DeepLearning\\LSTMTrain\\LSTMTrain.py",
    "codePath": "DeepLearning\\LSTMTrain\\LSTMTrain.py",
    "git": {
        "remote": "https://github.com/JoaquinAyzanoa/Glaciers_NeurIPS.git",
        "commit": "530212a2be42656f3ac17eb72d94efe179b0c392"
    },
    "email": "joaquinayzanoa@gmail.com",
    "root": "C:/Users/joaqu/OneDrive/Documentos/FAU/Project glaciar/Glaciers_NeurIPS",
    "host": "JoaquinLPT_RTX",
    "username": "joaqu",
    "executable": "C:\\Users\\joaqu\\anaconda3\\envs\\glaciar\\python.exe",
    "cpu_count": 8,
    "cpu_count_logical": 16,
    "cpu_freq": {
        "current": 2018.0,
        "min": 0.0,
        "max": 3801.0
    },
    "cpu_freq_per_core": [
        {
            "current": 2018.0,
            "min": 0.0,
            "max": 3801.0
        }
    ],
    "disk": {
        "/": {
            "total": 929.2880821228027,
            "used": 514.2726554870605
        }
    },
    "gpu": "NVIDIA GeForce RTX 4060 Laptop GPU",
    "gpu_count": 1,
    "gpu_devices": [
        {
            "name": "NVIDIA GeForce RTX 4060 Laptop GPU",
            "memory_total": 8585740288
        }
    ],
    "memory": {
        "total": 15.189807891845703
    }
}
